pycfalias/__init__.py
pycfalias/config.py
pycfalias/formatting.py
pycfalias/pycfalias.py
pycfalias_elielg-0.0.1.dist-info/LICENSE
pycfalias_elielg-0.0.1.dist-info/METADATA
pycfalias_elielg-0.0.1.dist-info/WHEEL
pycfalias_elielg-0.0.1.dist-info/top_level.txt
pycfalias_elielg-0.0.1.dist-info/RECORD
