Metadata-Version: 2.1
Name: pycfalias-elielg
Version: 0.0.1
Summary: Easy Cloudflare email alias management
Author-email: Eliel Garcia <inbox@eliel-garcia.com>
Project-URL: Homepage, https://github.com/ellie-gar/pycfalias
Project-URL: Bug Tracker, https://github.com/ellie-gar/pycfalias/issues
Classifier: Programming Language :: Python :: 3
Classifier: License :: OSI Approved :: MIT License
Classifier: Operating System :: OS Independent
Requires-Python: >=3.7
License-File: LICENSE
